README.md
export_torrent_cache.py
setup.py
export_torrent_cache.egg-info/PKG-INFO
export_torrent_cache.egg-info/SOURCES.txt
export_torrent_cache.egg-info/dependency_links.txt
export_torrent_cache.egg-info/entry_points.txt
export_torrent_cache.egg-info/requires.txt
export_torrent_cache.egg-info/top_level.txt