Metadata-Version: 2.1
Name: export-torrent-cache
Version: 0.1
Summary: Export/backup the cache directory of a torrent client, restoring original filenames and organized by tracker
Home-page: https://github.com/codeclem/export_torrent_cache
Author: codeclem
Author-email: 25412578+codeclem@users.noreply.github.com
License: MIT
Platform: UNKNOWN
Requires-Python: >=3.6
